{"data":"18/05/02","radars":{"fm":{"pdRC":"99.81","pdPR":"91.06","pdA":"100.00","pdC":"99.77","pdIncorValA":"0.00","pdIncorValC":"0.00","pdfalsecode":"0.00","RCpdA":"100.00","RCpdC":"100.00","RCpdIncorValA":"0.00","RCpdIncorValC":"0.00","RCpdfalsecode":"0.00","ratefalsetrgt":"0.00","ratemultitrgt":"0.01","ratesplittrgt":"0.00","raterefl.":"0.00","ratesidelobe":"0.00","Rangebias":"0.00","Gainbias":"0.00","Azimbias":"0.00","Timebias":"0.00","plotstddevRange":"0.00","plotstddevAzim.":"0.00"},"pl":{"pdRC":"99.82","pdPR":"95.78","pdA":"100.00","pdC":"100.00","pdIncorValA":"0.00","pdIncorValC":"0.00","pdfalsecode":"0.00","RCpdA":"100.00","RCpdC":"99.99","RCpdIncorValA":"0.00","RCpdIncorValC":"0.00","RCpdfalsecode":"0.00","ratefalsetrgt":"0.00","ratemultitrgt":"0.01","ratesplittrgt":"0.01","raterefl.":"0.00","ratesidelobe":"0.00","Rangebias":"0.00","Gainbias":"0.00","Azimbias":"0.00","Timebias":"0.00","plotstddevRange":"0.00","plotstddevAzim.":"0.00"},"mc":{"pdRC":"99.02","pdPR":"96.22","pdA":"0.00","pdC":"0.00","pdIncorValA":"0.00","pdIncorValC":"0.00","pdfalsecode":"0.00","RCpdA":"99.92","RCpdC":"99.93","RCpdIncorValA":"0.00","RCpdIncorValC":"0.00","RCpdfalsecode":"0.00","ratefalsetrgt":"0.00","ratemultitrgt":"0.00","ratesplittrgt":"0.00","raterefl.":"0.00","ratesidelobe":"0.00","Rangebias":"0.00","Gainbias":"0.00","Azimbias":"0.00","Timebias":"0.00","plotstddevRange":"0.00","plotstddevAzim.":"0.00"},"ol":{"pdRC":"99.10","pdPR":"86.19","pdA":"0.00","pdC":"0.00","pdIncorValA":"0.00","pdIncorValC":"0.00","pdfalsecode":"0.00","RCpdA":"99.97","RCpdC":"99.98","RCpdIncorValA":"0.00","RCpdIncorValC":"0.00","RCpdfalsecode":"0.00","ratefalsetrgt":"0.00","ratemultitrgt":"0.00","ratesplittrgt":"0.00","raterefl.":"0.00","ratesidelobe":"0.00","Rangebias":"0.00","Gainbias":"0.00","Azimbias":"0.00","Timebias":"0.00","plotstddevRange":"0.00","plotstddevAzim.":"0.00"},"le":{"pdRC":"99.74","pdPR":"92.19","pdA":"100.00","pdC":"100.00","pdIncorValA":"0.00","pdIncorValC":"0.00","pdfalsecode":"0.00","RCpdA":"100.00","RCpdC":"99.99","RCpdIncorValA":"0.00","RCpdIncorValC":"0.00","RCpdfalsecode":"0.00","ratefalsetrgt":"0.00","ratemultitrgt":"0.03","ratesplittrgt":"0.01","raterefl.":"0.02","ratesidelobe":"0.00","Rangebias":"0.00","Gainbias":"0.00","Azimbias":"0.00","Timebias":"0.00","plotstddevRange":"0.00","plotstddevAzim.":"0.00"},"pe":{"pdRC":"99.46","pdPR":"91.35","pdA":"99.04","pdC":"100.00","pdIncorValA":"0.00","pdIncorValC":"0.00","pdfalsecode":"0.00","RCpdA":"99.53","RCpdC":"99.52","RCpdIncorValA":"0.00","RCpdIncorValC":"0.00","RCpdfalsecode":"0.00","ratefalsetrgt":"0.00","ratemultitrgt":"0.04","ratesplittrgt":"0.00","raterefl.":"0.04","ratesidelobe":"0.00","Rangebias":"0.00","Gainbias":"0.00","Azimbias":"0.00","Timebias":"0.00","plotstddevRange":"0.00","plotstddevAzim.":"0.00"},"ra":{"pdRC":"99.77","pdPR":"92.75","pdA":"97.99","pdC":"92.82","pdIncorValA":"0.00","pdIncorValC":"0.86","pdfalsecode":"1.72","RCpdA":"99.68","RCpdC":"99.68","RCpdIncorValA":"0.00","RCpdIncorValC":"0.00","RCpdfalsecode":"0.00","ratefalsetrgt":"0.00","ratemultitrgt":"0.01","ratesplittrgt":"0.01","raterefl.":"0.00","ratesidelobe":"0.00","Rangebias":"0.00","Gainbias":"0.00","Azimbias":"0.00","Timebias":"0.00","plotstddevRange":"0.00","plotstddevAzim.":"0.00"},"fs":{"pdRC":"99.80","pdPR":"83.04","pdA":"100.00","pdC":"99.11","pdIncorValA":"0.00","pdIncorValC":"0.22","pdfalsecode":"0.22","RCpdA":"100.00","RCpdC":"99.99","RCpdIncorValA":"0.00","RCpdIncorValC":"0.00","RCpdfalsecode":"0.00","ratefalsetrgt":"0.00","ratemultitrgt":"0.03","ratesplittrgt":"0.00","raterefl.":"0.03","ratesidelobe":"0.00","Rangebias":"0.00","Gainbias":"0.00","Azimbias":"0.00","Timebias":"0.00","plotstddevRange":"0.00","plotstddevAzim.":"0.00"},"cc":{"pdRC":"99.97","pdPR":"-","pdA":"0.00","pdC":"0.00","pdIncorValA":"0.00","pdIncorValC":"0.00","pdfalsecode":"0.00","RCpdA":"99.99","RCpdC":"100.00","RCpdIncorValA":"0.00","RCpdIncorValC":"0.00","RCpdfalsecode":"0.00","ratefalsetrgt":"0.00","ratemultitrgt":"0.00","ratesplittrgt":"0.00","raterefl.":"0.00","ratesidelobe":"0.00","Rangebias":"0.00","Gainbias":"0.00","Azimbias":"0.00","Timebias":"0.00","plotstddevRange":"0.00","plotstddevAzim.":"0.00"},"fr":{"pdRC":"99.44","pdPR":"94.43","pdA":"0.00","pdC":"0.00","pdIncorValA":"0.00","pdIncorValC":"0.00","pdfalsecode":"0.00","RCpdA":"100.00","RCpdC":"100.00","RCpdIncorValA":"0.00","RCpdIncorValC":"0.00","RCpdfalsecode":"0.00","ratefalsetrgt":"0.00","ratemultitrgt":"0.00","ratesplittrgt":"0.00","raterefl.":"0.00","ratesidelobe":"0.00","Rangebias":"0.00","Gainbias":"0.00","Azimbias":"0.00","Timebias":"0.00","plotstddevRange":"0.00","plotstddevAzim.":"0.00"},"lz":{"pdRC":"99.88","pdPR":"92.25","pdA":"0.00","pdC":"0.00","pdIncorValA":"0.00","pdIncorValC":"0.00","pdfalsecode":"0.00","RCpdA":"99.82","RCpdC":"99.86","RCpdIncorValA":"0.00","RCpdIncorValC":"0.00","RCpdfalsecode":"0.00","ratefalsetrgt":"0.00","ratemultitrgt":"0.00","ratesplittrgt":"0.00","raterefl.":"0.00","ratesidelobe":"0.00","Rangebias":"0.00","Gainbias":"0.00","Azimbias":"0.00","Timebias":"0.00","plotstddevRange":"0.00","plotstddevAzim.":"0.00"},"mo":{"pdRC":"99.94","pdPR":"93.71","pdA":"100.00","pdC":"100.00","pdIncorValA":"0.00","pdIncorValC":"0.00","pdfalsecode":"0.00","RCpdA":"99.98","RCpdC":"99.99","RCpdIncorValA":"0.00","RCpdIncorValC":"0.00","RCpdfalsecode":"0.00","ratefalsetrgt":"0.00","ratemultitrgt":"0.01","ratesplittrgt":"0.01","raterefl.":"0.00","ratesidelobe":"0.00","Rangebias":"0.00","Gainbias":"0.00","Azimbias":"0.00","Timebias":"0.00","plotstddevRange":"0.00","plotstddevAzim.":"0.00"},"na":{"pdRC":"94.76","pdPR":"95.09","pdA":"97.96","pdC":"97.55","pdIncorValA":"0.00","pdIncorValC":"0.00","pdfalsecode":"0.00","RCpdA":"100.00","RCpdC":"99.91","RCpdIncorValA":"0.00","RCpdIncorValC":"0.00","RCpdfalsecode":"0.00","ratefalsetrgt":"0.00","ratemultitrgt":"0.01","ratesplittrgt":"0.01","raterefl.":"0.00","ratesidelobe":"0.00","Rangebias":"0.00","Gainbias":"0.00","Azimbias":"0.00","Timebias":"0.00","plotstddevRange":"0.00","plotstddevAzim.":"0.00"},"us":{"pdRC":"99.43","pdPR":"92.42","pdA":"0.00","pdC":"0.00","pdIncorValA":"0.00","pdIncorValC":"0.00","pdfalsecode":"0.00","RCpdA":"99.92","RCpdC":"99.92","RCpdIncorValA":"0.01","RCpdIncorValC":"0.00","RCpdfalsecode":"0.01","ratefalsetrgt":"0.00","ratemultitrgt":"0.01","ratesplittrgt":"0.01","raterefl.":"0.00","ratesidelobe":"0.00","Rangebias":"0.00","Gainbias":"0.00","Azimbias":"0.00","Timebias":"0.00","plotstddevRange":"0.00","plotstddevAzim.":"0.00"},"ms":{"pdRC":"99.47","pdPR":"90.87","pdA":"100.00","pdC":"100.00","pdIncorValA":"0.00","pdIncorValC":"0.00","pdfalsecode":"0.00","RCpdA":"99.97","RCpdC":"99.99","RCpdIncorValA":"0.00","RCpdIncorValC":"0.00","RCpdfalsecode":"0.00","ratefalsetrgt":"0.02","ratemultitrgt":"0.01","ratesplittrgt":"0.01","raterefl.":"0.00","ratesidelobe":"0.00","Rangebias":"0.00","Gainbias":"0.00","Azimbias":"0.00","Timebias":"0.00","plotstddevRange":"0.00","plotstddevAzim.":"0.00"},"ma":{"pdRC":"97.88","pdPR":"97.08","pdA":"100.00","pdC":"100.00","pdIncorValA":"0.00","pdIncorValC":"0.00","pdfalsecode":"0.00","RCpdA":"99.94","RCpdC":"99.93","RCpdIncorValA":"0.00","RCpdIncorValC":"0.00","RCpdfalsecode":"0.00","ratefalsetrgt":"0.01","ratemultitrgt":"0.00","ratesplittrgt":"0.00","raterefl.":"0.00","ratesidelobe":"0.00","Rangebias":"0.00","Gainbias":"0.00","Azimbias":"0.00","Timebias":"0.00","plotstddevRange":"0.00","plotstddevAzim.":"0.00"}}}