{"data":"18/05/05","radars":{"fm":{"pdRC":"99.82","pdPR":"93.64","pdA":"100.00","pdC":"100.00","pdIncorValA":"0.00","pdIncorValC":"0.00","pdfalsecode":"0.00","RCpdA":"100.00","RCpdC":"100.00","RCpdIncorValA":"0.00","RCpdIncorValC":"0.00","RCpdfalsecode":"0.00","ratefalsetrgt":"0.00","ratemultitrgt":"0.00","ratesplittrgt":"0.00","raterefl.":"0.00","ratesidelobe":"0.00","Rangebias":"0.00","Gainbias":"0.00","Azimbias":"0.00","Timebias":"0.00","plotstddevRange":"0.00","plotstddevAzim.":"0.00"},"pl":{"pdRC":"99.77","pdPR":"95.75","pdA":"0.00","pdC":"0.00","pdIncorValA":"0.00","pdIncorValC":"0.00","pdfalsecode":"0.00","RCpdA":"99.99","RCpdC":"100.00","RCpdIncorValA":"0.00","RCpdIncorValC":"0.00","RCpdfalsecode":"0.00","ratefalsetrgt":"0.00","ratemultitrgt":"0.01","ratesplittrgt":"0.01","raterefl.":"0.00","ratesidelobe":"0.00","Rangebias":"0.00","Gainbias":"0.00","Azimbias":"0.00","Timebias":"0.00","plotstddevRange":"0.00","plotstddevAzim.":"0.00"},"mc":{"pdRC":"99.18","pdPR":"96.48","pdA":"0.00","pdC":"0.00","pdIncorValA":"0.00","pdIncorValC":"0.00","pdfalsecode":"0.00","RCpdA":"99.91","RCpdC":"99.92","RCpdIncorValA":"0.00","RCpdIncorValC":"0.00","RCpdfalsecode":"0.00","ratefalsetrgt":"0.00","ratemultitrgt":"0.00","ratesplittrgt":"0.00","raterefl.":"0.00","ratesidelobe":"0.00","Rangebias":"0.00","Gainbias":"0.00","Azimbias":"0.00","Timebias":"0.00","plotstddevRange":"0.00","plotstddevAzim.":"0.00"},"ol":{"pdRC":"99.28","pdPR":"89.06","pdA":"0.00","pdC":"0.00","pdIncorValA":"0.00","pdIncorValC":"0.00","pdfalsecode":"0.00","RCpdA":"99.98","RCpdC":"99.98","RCpdIncorValA":"0.00","RCpdIncorValC":"0.00","RCpdfalsecode":"0.00","ratefalsetrgt":"0.00","ratemultitrgt":"0.00","ratesplittrgt":"0.00","raterefl.":"0.00","ratesidelobe":"0.00","Rangebias":"0.00","Gainbias":"0.00","Azimbias":"0.00","Timebias":"0.00","plotstddevRange":"0.00","plotstddevAzim.":"0.00"},"le":{"pdRC":"99.67","pdPR":"91.93","pdA":"0.00","pdC":"0.00","pdIncorValA":"0.00","pdIncorValC":"0.00","pdfalsecode":"0.00","RCpdA":"99.99","RCpdC":"99.99","RCpdIncorValA":"0.01","RCpdIncorValC":"0.00","RCpdfalsecode":"0.01","ratefalsetrgt":"0.00","ratemultitrgt":"0.08","ratesplittrgt":"0.01","raterefl.":"0.07","ratesidelobe":"0.00","Rangebias":"0.00","Gainbias":"0.00","Azimbias":"0.00","Timebias":"0.00","plotstddevRange":"0.00","plotstddevAzim.":"0.00"},"pe":{"pdRC":"99.62","pdPR":"90.45","pdA":"99.44","pdC":"100.00","pdIncorValA":"0.00","pdIncorValC":"0.00","pdfalsecode":"0.00","RCpdA":"99.52","RCpdC":"99.51","RCpdIncorValA":"0.00","RCpdIncorValC":"0.00","RCpdfalsecode":"0.00","ratefalsetrgt":"0.00","ratemultitrgt":"0.01","ratesplittrgt":"0.00","raterefl.":"0.01","ratesidelobe":"0.00","Rangebias":"0.00","Gainbias":"0.00","Azimbias":"0.00","Timebias":"0.00","plotstddevRange":"0.00","plotstddevAzim.":"0.00"},"ra":{"pdRC":"99.88","pdPR":"94.59","pdA":"0.00","pdC":"0.00","pdIncorValA":"0.00","pdIncorValC":"0.00","pdfalsecode":"0.00","RCpdA":"99.64","RCpdC":"99.66","RCpdIncorValA":"0.00","RCpdIncorValC":"0.00","RCpdfalsecode":"0.00","ratefalsetrgt":"0.00","ratemultitrgt":"0.01","ratesplittrgt":"0.00","raterefl.":"0.00","ratesidelobe":"0.00","Rangebias":"0.00","Gainbias":"0.00","Azimbias":"0.00","Timebias":"0.00","plotstddevRange":"0.00","plotstddevAzim.":"0.00"},"fs":{"pdRC":"99.86","pdPR":"84.05","pdA":"100.00","pdC":"100.00","pdIncorValA":"0.00","pdIncorValC":"0.00","pdfalsecode":"0.00","RCpdA":"100.00","RCpdC":"99.99","RCpdIncorValA":"0.00","RCpdIncorValC":"0.00","RCpdfalsecode":"0.00","ratefalsetrgt":"0.00","ratemultitrgt":"0.00","ratesplittrgt":"0.00","raterefl.":"0.00","ratesidelobe":"0.00","Rangebias":"0.00","Gainbias":"0.00","Azimbias":"0.00","Timebias":"0.00","plotstddevRange":"0.00","plotstddevAzim.":"0.00"},"fr":{"pdRC":"99.45","pdPR":"94.69","pdA":"100.00","pdC":"98.68","pdIncorValA":"0.00","pdIncorValC":"0.00","pdfalsecode":"0.00","RCpdA":"100.00","RCpdC":"99.99","RCpdIncorValA":"0.00","RCpdIncorValC":"0.00","RCpdfalsecode":"0.00","ratefalsetrgt":"0.00","ratemultitrgt":"0.00","ratesplittrgt":"0.00","raterefl.":"0.00","ratesidelobe":"0.00","Rangebias":"0.00","Gainbias":"0.00","Azimbias":"0.00","Timebias":"0.00","plotstddevRange":"0.00","plotstddevAzim.":"0.00"},"lz":{"pdRC":"99.96","pdPR":"95.78","pdA":"0.00","pdC":"0.00","pdIncorValA":"0.00","pdIncorValC":"0.00","pdfalsecode":"0.00","RCpdA":"99.84","RCpdC":"99.86","RCpdIncorValA":"0.00","RCpdIncorValC":"0.00","RCpdfalsecode":"0.00","ratefalsetrgt":"0.00","ratemultitrgt":"0.01","ratesplittrgt":"0.01","raterefl.":"0.01","ratesidelobe":"0.00","Rangebias":"0.00","Gainbias":"0.00","Azimbias":"0.00","Timebias":"0.00","plotstddevRange":"0.00","plotstddevAzim.":"0.00"},"mo":{"pdRC":"99.93","pdPR":"95.08","pdA":"0.00","pdC":"0.00","pdIncorValA":"0.00","pdIncorValC":"0.00","pdfalsecode":"0.00","RCpdA":"99.99","RCpdC":"100.00","RCpdIncorValA":"0.00","RCpdIncorValC":"0.00","RCpdfalsecode":"0.00","ratefalsetrgt":"0.00","ratemultitrgt":"0.00","ratesplittrgt":"0.00","raterefl.":"0.00","ratesidelobe":"0.00","Rangebias":"0.00","Gainbias":"0.00","Azimbias":"0.00","Timebias":"0.00","plotstddevRange":"0.00","plotstddevAzim.":"0.00"},"na":{"pdRC":"95.56","pdPR":"96.92","pdA":"100.00","pdC":"100.00","pdIncorValA":"0.00","pdIncorValC":"0.00","pdfalsecode":"0.00","RCpdA":"100.00","RCpdC":"99.91","RCpdIncorValA":"0.00","RCpdIncorValC":"0.00","RCpdfalsecode":"0.00","ratefalsetrgt":"0.00","ratemultitrgt":"0.01","ratesplittrgt":"0.00","raterefl.":"0.00","ratesidelobe":"0.00","Rangebias":"0.00","Gainbias":"0.00","Azimbias":"0.00","Timebias":"0.00","plotstddevRange":"0.00","plotstddevAzim.":"0.00"},"us":{"pdRC":"99.62","pdPR":"92.92","pdA":"0.00","pdC":"0.00","pdIncorValA":"0.00","pdIncorValC":"0.00","pdfalsecode":"0.00","RCpdA":"99.94","RCpdC":"99.93","RCpdIncorValA":"0.00","RCpdIncorValC":"0.00","RCpdfalsecode":"0.00","ratefalsetrgt":"0.00","ratemultitrgt":"0.00","ratesplittrgt":"0.00","raterefl.":"0.00","ratesidelobe":"0.00","Rangebias":"0.00","Gainbias":"0.00","Azimbias":"0.00","Timebias":"0.00","plotstddevRange":"0.00","plotstddevAzim.":"0.00"},"ms":{"pdRC":"99.43","pdPR":"93.47","pdA":"0.00","pdC":"0.00","pdIncorValA":"0.00","pdIncorValC":"0.00","pdfalsecode":"0.00","RCpdA":"99.98","RCpdC":"99.98","RCpdIncorValA":"0.00","RCpdIncorValC":"0.00","RCpdfalsecode":"0.00","ratefalsetrgt":"0.00","ratemultitrgt":"0.01","ratesplittrgt":"0.00","raterefl.":"0.00","ratesidelobe":"0.01","Rangebias":"0.00","Gainbias":"0.00","Azimbias":"0.00","Timebias":"0.00","plotstddevRange":"0.00","plotstddevAzim.":"0.00"},"ma":{"pdRC":"98.49","pdPR":"97.65","pdA":"0.00","pdC":"0.00","pdIncorValA":"0.00","pdIncorValC":"0.00","pdfalsecode":"0.00","RCpdA":"99.90","RCpdC":"99.91","RCpdIncorValA":"0.00","RCpdIncorValC":"0.00","RCpdfalsecode":"0.00","ratefalsetrgt":"0.00","ratemultitrgt":"0.00","ratesplittrgt":"0.00","raterefl.":"0.00","ratesidelobe":"0.00","Rangebias":"0.00","Gainbias":"0.00","Azimbias":"0.00","Timebias":"0.00","plotstddevRange":"0.00","plotstddevAzim.":"0.00"}}}